README.md
setup.py
msAuto/__init__.py
msAuto/main.py
msAuto.egg-info/PKG-INFO
msAuto.egg-info/SOURCES.txt
msAuto.egg-info/dependency_links.txt
msAuto.egg-info/top_level.txt