Metadata-Version: 1.1
Name: msAuto
Version: 0.0.1
Summary: A Projet Python package
Home-page: https://github.com/MehdiSellamiAdministrator
Author: Sellami Mehdi
Author-email: sellamimehdi87@gmail.com
License: UNKNOWN
Platform: UNKNOWN
Classifier: Programming Language :: Python :: 3
Classifier: License :: OSI Approved :: MIT License
Classifier: Operating System :: OS Independent
